LICENSE
huemon/__init__.py
huemon/__main__.py
huemon/api/__init__.py
huemon/api/api.py
huemon/api/api_factory.py
huemon/api/api_interface.py
huemon/api/cached_api.py
huemon/api_server.py
huemon/commands/__init__.py
huemon/commands/command_handler.py
huemon/commands/hue_command_interface.py
huemon/commands/internal/agent_command.py
huemon/commands/internal/discover_command.py
huemon/commands/internal/light_command.py
huemon/commands/internal/sensor_command.py
huemon/commands/internal/system_command.py
huemon/config.example.yml
huemon/discoveries/__init__.py
huemon/discoveries/discovery_interface.py
huemon/discoveries/internal/batteries_discovery.py
huemon/discoveries/internal/lights_discovery.py
huemon/discoveries/internal/sensors_discovery.py
huemon/infrastructure/__init__.py
huemon/infrastructure/bootstrapper.py
huemon/infrastructure/config_factory.py
huemon/infrastructure/logger_factory.py
huemon/infrastructure/plugin_loader.py
huemon/infrastructure/urllib_safe_opener.py
huemon/utils/__init__.py
huemon/utils/assertions.py
huemon/utils/caching.py
huemon/utils/const.py
huemon/utils/errors.py
huemon/utils/paths.py
huemon/utils/plugins.py
huemon/utils/threading.py
huemon-2.0.4.dist-info/LICENSE
huemon-2.0.4.dist-info/METADATA
huemon-2.0.4.dist-info/WHEEL
huemon-2.0.4.dist-info/RECORD
