Metadata-Version: 2.1
Name: huemon
Version: 2.0.4
Summary: Monitor your Philips Hue network
Home-page: https://github.com/edeckers/huemon
License: MPL-2.0
Keywords: Hue,Monitoring,Zabbix,Zigbee
Author: Ely Deckers
Maintainer: Ely Deckers
Requires-Python: >=3.9,<4.0
Classifier: Environment :: Console
Classifier: License :: OSI Approved
Classifier: Operating System :: MacOS
Classifier: Operating System :: POSIX :: Linux
Classifier: Programming Language :: Python :: 3
Classifier: Programming Language :: Python :: 3.9
Classifier: Programming Language :: Python :: 3.10
Classifier: Programming Language :: Python :: 3.11
Classifier: Programming Language :: Python :: 3.12
Classifier: Programming Language :: Python :: 3.13
Classifier: Programming Language :: Python :: 3.8
Classifier: Topic :: System :: Logging
Classifier: Topic :: System :: Monitoring
Requires-Dist: PyYAML (>=6.0,<7.0)
Requires-Dist: fastapi (>=0.115.6,<0.116.0)
Requires-Dist: pyella (>=2.0.0,<3.0.0)
Requires-Dist: types-PyYAML (>=6.0.4,<7.0.0)
Requires-Dist: uvicorn (>=0.17.5,<0.18.0)
Project-URL: Documentation, https://github.com/edeckers/huemon
Project-URL: Repository, https://github.com/edeckers/huemon.git
